django_fahrenheit/__init__.py
django_fahrenheit/admin.py
django_fahrenheit/apps.py
django_fahrenheit/exceptions.py
django_fahrenheit/http.py
django_fahrenheit/middleware.py
django_fahrenheit/migrations/0001_initial.py
django_fahrenheit/migrations/__init__.py
django_fahrenheit/models.py
django_fahrenheit/settings.py
django_fahrenheit/templatetags/__init__.py
django_fahrenheit/templatetags/fahrenheit_tags.py
django_fahrenheit/utils.py
django_fahrenheit/views.py
django_fahrenheit-0.1.4.dist-info/LICENSE
django_fahrenheit-0.1.4.dist-info/WHEEL
django_fahrenheit-0.1.4.dist-info/METADATA
django_fahrenheit-0.1.4.dist-info/RECORD
