Metadata-Version: 2.1
Name: django-fahrenheit
Version: 0.1.4
Summary: A tool for easily restrict access to some project URLs or even objects for legal reasons.
Home-page: https://github.com/marazmiki/django-fahrenheit
License: MIT
Keywords: django,fahrenheit,451,government,censorship,legal,restriction,deny
Author: Mikhail Porokhovnichenko
Author-email: marazmiki@gmail.com
Requires-Python: >=3.6,<4.0
Classifier: Development Status :: 4 - Beta
Classifier: Environment :: Web Environment
Classifier: Framework :: Django
Classifier: Framework :: Django :: 2.1
Classifier: Framework :: Django :: 2.2
Classifier: Framework :: Django :: 3.0
Classifier: Intended Audience :: Developers
Classifier: License :: OSI Approved :: MIT License
Classifier: Programming Language :: Python
Classifier: Programming Language :: Python :: 3
Classifier: Programming Language :: Python :: 3.6
Classifier: Programming Language :: Python :: 3.7
Classifier: Programming Language :: Python :: 3.8
Classifier: Topic :: Internet :: WWW/HTTP
Classifier: Topic :: Internet :: WWW/HTTP :: Dynamic Content
Classifier: Topic :: Software Development :: Libraries :: Python Modules
Requires-Dist: django-generic-helpers (>=1.0,<2.0)
Requires-Dist: geoip2 (>=2.9,<3.0)
Project-URL: Repository, https://github.com/marazmiki/django-fahrenheit
